{"platform":"bugcrowd","program_name":"Reference Information","program_url":"https://bugcrowd.com/engagements/okta","scope_assets":["Cloud Identity and Mobility Management Service"],"exclusions":["Okta is a cloud-based identity service that connects people to their applications from any device","anywhere","anytime. The Okta Identity Cloud provides directory services","single sign-on","strong authentication","provisioning","mobile device management and API access management. It comes with built-in reporting","and integrates deeply with cloud","mobile and on-premises applications","directories and identity management systems."],"reward_range":"If the debug mode doesn't show up, completely close out the application and retry.","reward_currency":"USD","payout_notes":"","allowed_techniques":[],"prohibited_techniques":[],"last_seen_at":"Cloud Identity and Mobility Management Service","source_snapshot_hash":"55b21ba152628852efba04539b163822b34861f1f23bc96a61f9aaba2b73981e"}