{
  "lastHeartbeatAt": "2026-03-26T11:47:00Z",
  "heartbeatCycle": 1,
  "automations": {
    "all_crons_removed": true,
    "note": "Infinitara reset directive 2026-03-26 01:03 UTC - all bounty/heartbeat crons deleted. No automated scanning, no proactive monitoring. Tools run on explicit request only."
  },
  "vectorMemory": {
    "status": "WORKING",
    "collections": {
      "agent_memory": "working",
      "pipeline_findings": "empty"
    }
  },
  "notes": [
    "26 Mar 11:47 - Memory flushed. Commit 6540b0bd (cleaned up bounty-pipeline build artifacts, added MEXC script)."
  ]
}
